willow/__init__.py
willow/image.py
willow/registry.py
willow/svg.py
willow/data/cascades/haarcascade_frontalface_alt2.xml
willow/optimizers/__init__.py
willow/optimizers/base.py
willow/optimizers/cwebp.py
willow/optimizers/gifsicle.py
willow/optimizers/jpegoptim.py
willow/optimizers/optipng.py
willow/optimizers/pngquant.py
willow/plugins/__init__.py
willow/plugins/opencv.py
willow/plugins/pillow.py
willow/plugins/wand.py
willow/utils/__init__.py
willow/utils/deprecation.py
willow-1.7.0.dist-info/LICENSE
willow-1.7.0.dist-info/WHEEL
willow-1.7.0.dist-info/METADATA
willow-1.7.0.dist-info/RECORD
