Metadata-Version: 2.1
Name: Willow
Version: 1.7.0
Summary: A Python image library that sits on top of Pillow, Wand and OpenCV
Keywords: Imaging
Author-email: Karl Hobley <karl@kaed.uk>
Maintainer-email: Wagtail Core team <hello@wagtail.org>
Requires-Python: >=3.8
Classifier: Development Status :: 5 - Production/Stable
Classifier: Topic :: Multimedia :: Graphics
Classifier: Topic :: Multimedia :: Graphics :: Graphics Conversion
Classifier: Intended Audience :: Developers
Classifier: License :: OSI Approved :: BSD License
Classifier: Operating System :: OS Independent
Classifier: Programming Language :: Python
Classifier: Programming Language :: Python :: 3
Classifier: Programming Language :: Python :: 3 :: Only
Classifier: Programming Language :: Python :: 3.8
Classifier: Programming Language :: Python :: 3.9
Classifier: Programming Language :: Python :: 3.10
Classifier: Programming Language :: Python :: 3.11
Classifier: Programming Language :: Python :: 3.12
Requires-Dist: filetype>=1.0.10,!=1.1.0
Requires-Dist: defusedxml>=0.7,<1.0
Requires-Dist: Sphinx>=7.0 ; extra == "docs"
Requires-Dist: sphinx-wagtail-theme>=6.1.1,<7.0 ; extra == "docs"
Requires-Dist: sphinxcontrib-spelling>=8.0,<9.0 ; extra == "docs"
Requires-Dist: sphinx_copybutton>=0.5 ; extra == "docs"
Requires-Dist: pillow-heif>=0.10.0,<1.0.0 ; extra == "heif" and ( python_version < '3.12')
Requires-Dist: pillow-heif>=0.13.0,<1.0.0 ; extra == "heif" and ( python_version >= '3.12')
Requires-Dist: Pillow>=9.1.0,<11.0.0 ; extra == "pillow"
Requires-Dist: willow[pillow,wand,heif] ; extra == "testing"
Requires-Dist: coverage[toml]>=7.2.7,<8.0 ; extra == "testing"
Requires-Dist: pre-commit>=3.4.0 ; extra == "testing"
Requires-Dist: Wand>=0.6,<1.0 ; extra == "wand"
Project-URL: Changelog, https://github.com/wagtail/Willow/blob/main/CHANGELOG.txt
Project-URL: Source, https://github.com/wagtail/Willow
Provides-Extra: docs
Provides-Extra: heif
Provides-Extra: pillow
Provides-Extra: testing
Provides-Extra: wand
